psychic_link/__init__.py
psychic_link/psychic.py
psychic_link-0.2.dist-info/METADATA
psychic_link-0.2.dist-info/WHEEL
psychic_link-0.2.dist-info/top_level.txt
psychic_link-0.2.dist-info/RECORD
