Metadata-Version: 2.1
Name: psychic-link
Version: 0.2
Summary: Psychic.dev is an open-source universal data connector for knowledgebases.
Author: Ayan Bandyopadhyay
Author-email: ayan@getsidekick.ai
Requires-Dist: requests
